README
setup.py
esgfpy/__init__.py
esgfpy/publish/__init__.py
esgfpy/publish/consts.py
esgfpy/publish/metadata_mappers.py
esgfpy/publish/models.py
esgfpy/publish/services.py
esgfpy/publish/utils.py
esgfpy/publish/drivers/__init__.py
esgfpy/publish/drivers/main_co2.py
esgfpy/publish/drivers/main_ncpp.py
esgfpy/publish/drivers/main_ytoc.py
esgfpy/publish/factories/__init__.py
esgfpy/publish/factories/datasets_factory.py
esgfpy/publish/factories/files_factory.py
esgfpy/publish/factories/utils.py
esgfpy/publish/parsers/__init__.py
esgfpy/publish/parsers/abstract_parser.py
esgfpy/publish/parsers/acos_parser.py
esgfpy/publish/parsers/airs_parser.py
esgfpy/publish/parsers/directory_parser.py
esgfpy/publish/parsers/filename_parser.py
esgfpy/publish/parsers/hdf_parser.py
esgfpy/publish/parsers/netcdf_parser.py
esgfpy/publish/parsers/oco2_parser.py
esgfpy/publish/parsers/optout_parser.py
esgfpy/publish/parsers/tes_parser.py
esgfpy/publish/parsers/tes_xml_parser.py
esgfpy/publish/parsers/xml_parser.py
esgfpy_publish.egg-info/PKG-INFO
esgfpy_publish.egg-info/SOURCES.txt
esgfpy_publish.egg-info/dependency_links.txt
esgfpy_publish.egg-info/requires.txt
esgfpy_publish.egg-info/top_level.txt