Metadata-Version: 1.1
Name: esgfpy-publish
Version: 0.9
Summary: Python client-side package for publishing data to the Earth System Grid Federation (ESGF)
Home-page: https://github.com/EarthSystemCoG/esgfpy-publish
Author: Luca Cinquini
Author-email: luca.cinquini@jpl.nasa.gov
License: ASF
Keywords: python publishing client ESGF earth system grid federation
Platform: UNKNOWN
Classifier: Development Status :: 4 - Beta
Classifier: Topic :: Utilities
Classifier: License :: OSI Approved :: Apache Software License
Classifier: Programming Language :: Python :: 2 :: Only
